tests/__init__.py
tests/test_segment_image.py
tests/__pycache__/__init__.cpython-38.pyc
tests/__pycache__/test_segment_image.cpython-38.pyc
visionlit/__init__.py
visionlit/main.c
visionlit/main.cpython-38-darwin.so
visionlit/__pycache__/__init__.cpython-38.pyc
visionlit/utils/utils.c
visionlit/utils/utils.cpython-38-darwin.so
visionlit/visionlit.egg-info/PKG-INFO
visionlit/visionlit.egg-info/SOURCES.txt
visionlit/visionlit.egg-info/dependency_links.txt
visionlit/visionlit.egg-info/requires.txt
visionlit/visionlit.egg-info/top_level.txt
visionlit-1.0.11.dist-info/LICENSE
visionlit-1.0.11.dist-info/METADATA
visionlit-1.0.11.dist-info/WHEEL
visionlit-1.0.11.dist-info/entry_points.txt
visionlit-1.0.11.dist-info/top_level.txt
visionlit-1.0.11.dist-info/RECORD
